{"stylesheet":{"sourceLinesOfCode":7,"linesOfCode":13,"size":173,"comments":{"total":0,"size":0},"embeddedContent":{"total":0,"totalUnique":0,"unique":{},"uniquenessRatio":0,"size":{"total":0,"ratio":0}}},"atrules":{"fontface":{"total":0,"totalUnique":0,"unique":[],"uniquenessRatio":1},"import":{"total":0,"totalUnique":0,"unique":{},"uniquenessRatio":0},"media":{"total":1,"totalUnique":1,"unique":{"(min-width: 100px)":1},"uniquenessRatio":1},"charset":{"total":0,"totalUnique":0,"unique":{},"uniquenessRatio":0},"supports":{"total":1,"totalUnique":1,"unique":{"(display: grid)":1},"uniquenessRatio":1},"keyframes":{"total":0,"totalUnique":0,"unique":{},"uniquenessRatio":0,"prefixed":{"total":0,"totalUnique":0,"unique":{},"uniquenessRatio":0,"ratio":0}},"container":{"total":0,"totalUnique":0,"unique":{},"uniquenessRatio":0}},"rules":{"total":2,"empty":{"total":0,"ratio":0},"selectors":{"min":1,"max":1,"mean":1,"mode":1,"median":1,"range":0,"sum":2,"items":[1,1]},"declarations":{"min":1,"max":2,"mean":1.5,"mode":1.5,"median":1.5,"range":1,"sum":3,"items":[1,2]}},"selectors":{"total":2,"totalUnique":2,"uniquenessRatio":1,"specificity":{"min":[0,0,2],"max":[0,1,0],"sum":[0,1,2],"mean":[0,0.5,1],"mode":[0,0.5,1],"median":[0,0.5,1],"items":[[0,1,0],[0,0,2]]},"complexity":{"min":1,"max":2,"mean":1.5,"mode":1.5,"median":1.5,"range":1,"sum":3,"total":2,"totalUnique":2,"unique":{"1":1,"2":1},"uniquenessRatio":1,"items":[1,2]},"id":{"total":0,"totalUnique":0,"unique":{},"uniquenessRatio":0,"ratio":0},"accessibility":{"total":0,"totalUnique":0,"unique":{},"uniquenessRatio":0,"ratio":0},"keyframes":{"total":0,"totalUnique":0,"unique":{},"uniquenessRatio":0,"ratio":0}},"declarations":{"total":3,"unique":{"total":3,"ratio":1},"importants":{"total":1,"ratio":0.3333333333333333,"inKeyframes":{"total":0,"ratio":0}}},"properties":{"total":3,"totalUnique":3,"unique":{"color":1,"content":1,"*zoom":1},"uniquenessRatio":1,"prefixed":{"total":0,"totalUnique":0,"unique":{},"uniquenessRatio":0,"ratio":0},"custom":{"total":0,"totalUnique":0,"unique":{},"uniquenessRatio":0,"ratio":0},"browserhacks":{"total":1,"totalUnique":1,"unique":{"*zoom":1},"uniquenessRatio":1,"ratio":0.3333333333333333}},"values":{"colors":{"total":1,"totalUnique":1,"unique":{"green":1},"uniquenessRatio":1,"itemsPerContext":{"color":{"total":1,"totalUnique":1,"unique":{"green":1},"uniquenessRatio":1}}},"fontFamilies":{"total":0,"totalUnique":0,"unique":{},"uniquenessRatio":0},"fontSizes":{"total":0,"totalUnique":0,"unique":{},"uniquenessRatio":0},"zindexes":{"total":0,"totalUnique":0,"unique":{},"uniquenessRatio":0},"textShadows":{"total":0,"totalUnique":0,"unique":{},"uniquenessRatio":0},"boxShadows":{"total":0,"totalUnique":0,"unique":{},"uniquenessRatio":0},"animations":{"durations":{"total":0,"totalUnique":0,"unique":{},"uniquenessRatio":0},"timingFunctions":{"total":0,"totalUnique":0,"unique":{},"uniquenessRatio":0}},"prefixes":{"total":0,"totalUnique":0,"unique":{},"uniquenessRatio":0},"units":{"total":0,"totalUnique":0,"unique":{},"uniquenessRatio":0,"itemsPerContext":{}}}}
